poetry_demo_sailesh/__init__.py
poetry_demo_sailesh-0.1.2.dist-info/METADATA
poetry_demo_sailesh-0.1.2.dist-info/WHEEL
poetry_demo_sailesh-0.1.2.dist-info/RECORD
