Metadata-Version: 2.4
Name: poetry-demo-sailesh
Version: 0.1.2
Summary: A demo project using Poetry and Pendulum
License: MIT
Keywords: poetry,pendulum,demo,python-packaging
Author: Sailesh Mishra
Author-email: sailesh.mishra@analog.com
Requires-Python: >=3.10
Classifier: License :: OSI Approved :: MIT License
Classifier: Operating System :: OS Independent
Classifier: Programming Language :: Python :: 3
Classifier: Programming Language :: Python :: 3.10
Classifier: Programming Language :: Python :: 3.11
Classifier: Programming Language :: Python :: 3.12
Classifier: Programming Language :: Python :: 3.13
Classifier: Programming Language :: Python :: 3.14
Requires-Dist: pendulum (>=3.1.0,<4.0.0)
Project-URL: Homepage, https://github.com/saileshmishraindia
Project-URL: Repository, https://github.com/saileshmishraindia/Chip-Manufacturing-Defect-Dataset-Pandas-Demonstration
